[
  {
    "full_name": "Blizzard/node-rdkafka",
    "stargazers_count": 2028,
    "open_issues_count": 95,
    "forks_count": 394
  },
  {
    "full_name": "apache/kafka",
    "stargazers_count": 26434,
    "open_issues_count": 1119,
    "forks_count": 13290
  },
  {
    "full_name": "tulios/kafkajs",
    "stargazers_count": 3478,
    "open_issues_count": 312,
    "forks_count": 487
  },
  {
    "full_name": "open-sauced/open-sauced",
    "stargazers_count": 900,
    "open_issues_count": 0,
    "forks_count": 815
  }
]