[
  {
    "full_name": "Blizzard/node-rdkafka",
    "stargazers_count": 1917,
    "open_issues_count": 52,
    "forks_count": 366
  },
  {
    "full_name": "apache/kafka",
    "stargazers_count": 23565,
    "open_issues_count": 1023,
    "forks_count": 12076
  },
  {
    "full_name": "tulios/kafkajs",
    "stargazers_count": 2956,
    "open_issues_count": 207,
    "forks_count": 407
  },
  {
    "full_name": "open-sauced/open-sauced",
    "stargazers_count": 806,
    "open_issues_count": 11,
    "forks_count": 443
  }
]